dnsrobocert/__init__.py
dnsrobocert/schema.yml
dnsrobocert/core/__init__.py
dnsrobocert/core/background.py
dnsrobocert/core/certbot.py
dnsrobocert/core/challenge.py
dnsrobocert/core/config.py
dnsrobocert/core/hooks.py
dnsrobocert/core/legacy.py
dnsrobocert/core/main.py
dnsrobocert/core/utils.py
dnsrobocert-3.26.1.dist-info/METADATA
dnsrobocert-3.26.1.dist-info/WHEEL
dnsrobocert-3.26.1.dist-info/entry_points.txt
dnsrobocert-3.26.1.dist-info/licenses/LICENSE
dnsrobocert-3.26.1.dist-info/RECORD
