Metadata-Version: 2.4
Name: dnsrobocert
Version: 3.26.1
Summary: A tool to manage your DNS-challenged TLS certificates
Project-URL: repository, https://github.com/adferrand/dnsrobocert
Project-URL: homepage, https://adferrand.github.io/dnsrobocert/
Author-email: Adrien Ferrand <ferrand.ad@gmail.com>
License-Expression: MIT
License-File: LICENSE
Keywords: dnsrobocert
Classifier: Development Status :: 3 - Alpha
Classifier: Intended Audience :: Developers
Classifier: Intended Audience :: System Administrators
Classifier: License :: OSI Approved :: MIT License
Classifier: Operating System :: Microsoft :: Windows
Classifier: Operating System :: POSIX
Classifier: Operating System :: Unix
Classifier: Programming Language :: Python
Classifier: Programming Language :: Python :: 3
Classifier: Programming Language :: Python :: 3.9
Classifier: Programming Language :: Python :: 3.10
Classifier: Programming Language :: Python :: 3.11
Classifier: Programming Language :: Python :: 3.12
Classifier: Programming Language :: Python :: 3.13
Classifier: Programming Language :: Python :: Implementation :: CPython
Classifier: Topic :: Utilities
Requires-Python: >=3.9
Requires-Dist: acme>=2
Requires-Dist: certbot>=2
Requires-Dist: cffi>=1
Requires-Dist: colorama>=0
Requires-Dist: coloredlogs>=14
Requires-Dist: cryptography>=2
Requires-Dist: dns-lexicon[full]>=3.14.0
Requires-Dist: dnspython>=2.1.0
Requires-Dist: jsonschema>=3
Requires-Dist: lxml>=4
Requires-Dist: pem>=20
Requires-Dist: pyopenssl>=19
Requires-Dist: pyyaml>=5
Requires-Dist: schedule>=0
Requires-Dist: tldextract>=3
